moonlette/__init__.py
moonlette/server.py
moonlette-0.0.1.dist-info/licenses/LICENSE
moonlette-0.0.1.dist-info/METADATA
moonlette-0.0.1.dist-info/WHEEL
moonlette-0.0.1.dist-info/top_level.txt
moonlette-0.0.1.dist-info/RECORD
